{"places":[{"id":"place 1","name":"A","namePositionX":247,"namePositionY":115.8125,"posX":267,"posY":150.8125,"connections":["Start Arc 1"],"nTokens":1},{"id":"place 2","name":"P2","namePositionX":472,"namePositionY":116.8125,"posX":492,"posY":151.8125,"connections":["Finish Arc 2"],"nTokens":0}],"transitions":[{"id":"transition 1","name":"T1","namePositionX":364,"namePositionY":118.8125,"posX":371.5,"posY":128.8125,"connections":["Finish Arc 1","Start Arc 2"],"isEnabled":false}],"arcs":[{"id":"Arc 1","name":"A1","type":"normal","startingPositionArc":[[292,150.8125,"place 1"]],"endPositionArc":[[371.5,150.8125,"transition 1"]],"start":"place 1","end":"transition 1","intermediatePoints":[],"isEnable":false,"weight":1,"weightPos":{"x":336.8589838486225,"y":170.81250000000003}},{"id":"Arc 2","name":"A2","type":"normal","startingPositionArc":[[396.5,151.8125,"transition 1"]],"endPositionArc":[[467,151.8125,"place 2"]],"start":"transition 1","end":"place 2","intermediatePoints":[],"isEnable":false,"weight":1,"weightPos":{"x":432.3589838486225,"y":171.81250000000003}}],"nPlaces":2,"nTransitions":1,"nArcs":2}